setup.py
debuilder/__init__.py
debuilder/executable.py
debuilder/pbuilder.py
debuilder/steps.py
debuilder/utils.py
debuilder.egg-info/PKG-INFO
debuilder.egg-info/SOURCES.txt
debuilder.egg-info/dependency_links.txt
debuilder.egg-info/requires.txt
debuilder.egg-info/top_level.txt