Metadata-Version: 1.1
Name: debuilder
Version: 0.3.1
Summary: Debian packages build tool
Home-page: https://github.com/bigbes/debgitbuild
Author: Bigbes
Author-email: bigbes@gmail.com
License: http://www.apache.org/licenses/LICENSE-2.0
Download-URL: https://github.com/bigbes/debgitbuild
Keywords: build,deb,packaging
Platform: UNKNOWN
Classifier: Development Status :: 3 - Alpha
Classifier: Programming Language :: Python
Classifier: Programming Language :: Python :: 2.6
Classifier: Programming Language :: Python :: 2.7
Classifier: Environment :: Console
Classifier: Intended Audience :: Developers
Classifier: License :: OSI Approved :: Apache Software License
Classifier: Topic :: Software Development
Classifier: Topic :: Software Development :: Libraries
Classifier: Topic :: Software Development :: Build Tools
Classifier: Topic :: Utilities
